mdb_bp/__init__.py
mdb_bp/bitmap.py
mdb_bp/config.py
mdb_bp/connection.py
mdb_bp/connector.py
mdb_bp/const.py
mdb_bp/driver.py
mdb_bp/file.py
mdb_bp/result.py
mdb_bp/row.py
mdb_bp/statement.py
mdb_bp/transaction.py
mdb_bp/utils.py
mdb_bp/protocol_buffers/__init__.py
mdb_bp/protocol_buffers/odbc_pb2.py
mdb_bp/protocol_buffers/odbc_pb2_grpc.py
tests/__init__.py
tests/test_config.py
tests/test_connection.py
tests/test_driver.py
tests/test_mdb.py
tests/test_result.py
tests/tests_deserialization.py
tests/tests_files.py
tests/tests_utils.py
mdb_bp-1.0.1.dist-info/METADATA
mdb_bp-1.0.1.dist-info/WHEEL
mdb_bp-1.0.1.dist-info/top_level.txt
mdb_bp-1.0.1.dist-info/RECORD
