Metadata-Version: 2.1
Name: mdb-bp
Version: 1.0.1
Summary: blockpoint Systems - MultiVersion Database (MDB) ODBC
Home-page: https://gitlab.com/blockpoint/mdb-odbc-python
Author: Blockpoint Systems
Author-email: <info@blockpointdb.com>
License: UNKNOWN
Keywords: blockpoint,mdb_bp,odbc,blockchain,database
Platform: UNKNOWN
Classifier: Development Status :: 3 - Alpha
Classifier: Intended Audience :: Developers
Classifier: Programming Language :: Python :: 2
Classifier: Programming Language :: Python :: 3
Classifier: Operating System :: MacOS :: MacOS X
Classifier: Operating System :: Microsoft :: Windows
Classifier: Topic :: Database
Requires-Dist: grpcio
Requires-Dist: grpcio-tools
Requires-Dist: google
